{
  "generated_at_utc": "2026-07-21T15:31:20.083429Z",
  "generated_at_et": "2026-07-21T11:31:20.083437-04:00",
  "version": 5,
  "tickers": [
    "IWM",
    "QQQ",
    "SPY",
    "AAPL",
    "AMZN",
    "GOOGL",
    "META",
    "MSFT",
    "NVDA",
    "AVGO",
    "PLTR",
    "TSLA",
    "MSTR",
    "MU",
    "ORCL",
    "NBIS",
    "JPM",
    "BABA",
    "COST",
    "NFLX",
    "UBER",
    "LLY",
    "CAT",
    "XOM",
    "IONQ",
    "RIVN",
    "WDC",
    "RKLB",
    "CVNA"
  ],
  "setup_timeframes": [
    "4H",
    "1D"
  ],
  "tier2_timeframe": "15Min",
  "proximity_alert_pct": 0.75,
  "min_runway_r": 2.0,
  "min_ftfc": 4,
  "ftfc_timeframes": [
    "1H",
    "2H",
    "4H",
    "1D",
    "1W"
  ],
  "armed_levels": [
    {
      "symbol": "MSFT",
      "setup_tf": "4H",
      "family": "inside",
      "pattern": "3-1-2",
      "direction": "bear",
      "trigger_side": "below",
      "level": 399.84,
      "invalidation": 402.68,
      "target": 396.32,
      "risk_reward": 1.24,
      "scale_level": 397.0,
      "runner_r": 1.24,
      "current_price": 398.74,
      "distance_pct": 0.275,
      "tier": "TIER2",
      "tier1_time": "2026-07-21T11:00:00-04:00",
      "tier2_time": "2026-07-21T11:00:00-04:00",
      "setup_bar_time": "2026-07-20T13:30:00-04:00",
      "setup_bar_closes_at": "2026-07-21T13:30:00-04:00",
      "minutes_to_next_15m": 15,
      "continuity": "4/5",
      "invalidated_by_opposite": false,
      "decision": {
        "passed": true,
        "score": 24,
        "runway_r": 7.46,
        "nearest_r": 3.59,
        "rungs": [
          {
            "tf": "2H",
            "level": 396.32,
            "r": 1.24,
            "gating": false
          },
          {
            "tf": "1D",
            "level": 389.65,
            "r": 3.59,
            "gating": true
          },
          {
            "tf": "1W",
            "level": 378.65,
            "r": 7.46,
            "gating": true
          }
        ],
        "continuity": {
          "4H": true,
          "1D": true
        },
        "ftfc": {
          "1H": true,
          "2H": true,
          "4H": true,
          "1D": true,
          "1W": false
        },
        "ftfc_aligned": 4,
        "nested_tfs": [
          "4H"
        ],
        "compressed": true,
        "reasons": [
          "pass: 2 gating rungs, nearest 3.6R, runway 7.5R, score 24"
        ]
      }
    },
    {
      "symbol": "AMZN",
      "setup_tf": "4H",
      "family": "inside",
      "pattern": "2-1-2",
      "direction": "bear",
      "trigger_side": "below",
      "level": 249.06,
      "invalidation": 250.83,
      "target": 246.72,
      "risk_reward": 1.33,
      "scale_level": 247.3,
      "runner_r": 1.33,
      "current_price": 248.0,
      "distance_pct": 0.43,
      "tier": "TIER2",
      "tier1_time": "2026-07-21T09:45:00-04:00",
      "tier2_time": "2026-07-21T09:45:00-04:00",
      "setup_bar_time": "2026-07-20T13:30:00-04:00",
      "setup_bar_closes_at": "2026-07-21T13:30:00-04:00",
      "minutes_to_next_15m": 15,
      "continuity": "3/5",
      "invalidated_by_opposite": false,
      "decision": {
        "passed": true,
        "score": 16,
        "runway_r": 3.1,
        "nearest_r": 3.1,
        "rungs": [
          {
            "tf": "2H",
            "level": 246.72,
            "r": 1.33,
            "gating": false
          },
          {
            "tf": "1W",
            "level": 243.59,
            "r": 3.1,
            "gating": true
          }
        ],
        "continuity": {
          "4H": true,
          "1D": true
        },
        "ftfc": {
          "1H": false,
          "2H": true,
          "4H": true,
          "1D": true,
          "1W": true
        },
        "ftfc_aligned": 4,
        "nested_tfs": [
          "4H"
        ],
        "compressed": true,
        "reasons": [
          "pass: 1 gating rungs, nearest 3.1R, runway 3.1R, score 16"
        ]
      }
    },
    {
      "symbol": "GOOGL",
      "setup_tf": "4H",
      "family": "inside",
      "pattern": "2-1-2",
      "direction": "bear",
      "trigger_side": "below",
      "level": 350.74,
      "invalidation": 353.71,
      "target": 347.59,
      "risk_reward": 1.06,
      "scale_level": 347.77,
      "runner_r": 1.06,
      "current_price": 347.83,
      "distance_pct": 0.83,
      "tier": "TIER2",
      "tier1_time": "2026-07-21T09:45:00-04:00",
      "tier2_time": "2026-07-21T09:45:00-04:00",
      "setup_bar_time": "2026-07-20T13:30:00-04:00",
      "setup_bar_closes_at": "2026-07-21T13:30:00-04:00",
      "minutes_to_next_15m": 15,
      "continuity": "5/5",
      "invalidated_by_opposite": false,
      "decision": {
        "passed": true,
        "score": 21,
        "runway_r": 3.16,
        "nearest_r": 3.16,
        "rungs": [
          {
            "tf": "2H",
            "level": 347.59,
            "r": 1.06,
            "gating": false
          },
          {
            "tf": "1W",
            "level": 341.36,
            "r": 3.16,
            "gating": true
          }
        ],
        "continuity": {
          "4H": true,
          "1D": true
        },
        "ftfc": {
          "1H": true,
          "2H": true,
          "4H": true,
          "1D": true,
          "1W": true
        },
        "ftfc_aligned": 5,
        "nested_tfs": [
          "4H",
          "1D"
        ],
        "compressed": true,
        "reasons": [
          "pass: 1 gating rungs, nearest 3.2R, runway 3.2R, score 21"
        ]
      }
    },
    {
      "symbol": "ORCL",
      "setup_tf": "4H",
      "family": "inside",
      "pattern": "2-1-2",
      "direction": "bull",
      "trigger_side": "above",
      "level": 123.88,
      "invalidation": 121.28,
      "target": 126.21,
      "risk_reward": 0.9,
      "scale_level": 126.48,
      "runner_r": 0.9,
      "current_price": 125.27,
      "distance_pct": 1.122,
      "tier": "TIER2",
      "tier1_time": "2026-07-21T09:45:00-04:00",
      "tier2_time": "2026-07-21T09:45:00-04:00",
      "setup_bar_time": "2026-07-20T13:30:00-04:00",
      "setup_bar_closes_at": "2026-07-21T13:30:00-04:00",
      "minutes_to_next_15m": 15,
      "continuity": "4/5",
      "invalidated_by_opposite": false,
      "decision": {
        "passed": true,
        "score": 22,
        "runway_r": 6.07,
        "nearest_r": 6.07,
        "rungs": [
          {
            "tf": "2H",
            "level": 126.21,
            "r": 0.9,
            "gating": false
          },
          {
            "tf": "1W",
            "level": 139.65,
            "r": 6.07,
            "gating": true
          }
        ],
        "continuity": {
          "4H": true,
          "1D": true
        },
        "ftfc": {
          "1H": false,
          "2H": true,
          "4H": true,
          "1D": true,
          "1W": true
        },
        "ftfc_aligned": 4,
        "nested_tfs": [
          "4H"
        ],
        "compressed": true,
        "reasons": [
          "pass: 1 gating rungs, nearest 6.1R, runway 6.1R, score 22"
        ]
      }
    },
    {
      "symbol": "AAPL",
      "setup_tf": "4H",
      "family": "f2",
      "pattern": "F2U",
      "direction": "bull",
      "trigger_side": "above",
      "level": 324.2,
      "invalidation": 322.22,
      "target": 328.45,
      "risk_reward": 2.15,
      "scale_level": 326.18,
      "runner_r": 2.15,
      "current_price": 328.38,
      "distance_pct": 1.291,
      "tier": "TIER2",
      "tier1_time": "2026-07-21T10:15:00-04:00",
      "tier2_time": "2026-07-21T10:15:00-04:00",
      "setup_bar_time": "2026-07-21T09:30:00-04:00",
      "setup_bar_closes_at": "2026-07-21T13:30:00-04:00",
      "minutes_to_next_15m": 15,
      "continuity": "5/5",
      "invalidated_by_opposite": false,
      "decision": {
        "passed": true,
        "score": 30,
        "runway_r": 5.45,
        "nearest_r": 2.81,
        "rungs": [
          {
            "tf": "2H",
            "level": 328.45,
            "r": 2.15,
            "gating": false
          },
          {
            "tf": "4H",
            "level": 329.76,
            "r": 2.81,
            "gating": true
          },
          {
            "tf": "1D",
            "level": 333.71,
            "r": 4.8,
            "gating": true
          },
          {
            "tf": "1W",
            "level": 334.99,
            "r": 5.45,
            "gating": true
          }
        ],
        "continuity": {
          "4H": true,
          "1D": true
        },
        "ftfc": {
          "1H": true,
          "2H": true,
          "4H": true,
          "1D": true,
          "1W": false
        },
        "ftfc_aligned": 4,
        "nested_tfs": [
          "4H",
          "1D"
        ],
        "compressed": true,
        "reasons": [
          "pass: 3 gating rungs, nearest 2.8R, runway 5.5R, score 30"
        ]
      }
    },
    {
      "symbol": "UBER",
      "setup_tf": "4H",
      "family": "f2",
      "pattern": "F2D",
      "direction": "bear",
      "trigger_side": "below",
      "level": 72.81,
      "invalidation": 72.99,
      "target": 71.66,
      "risk_reward": 6.39,
      "scale_level": 72.63,
      "runner_r": 6.39,
      "current_price": 71.85,
      "distance_pct": 1.319,
      "tier": "TIER2",
      "tier1_time": "2026-07-21T10:00:00-04:00",
      "tier2_time": "2026-07-21T10:00:00-04:00",
      "setup_bar_time": "2026-07-21T09:30:00-04:00",
      "setup_bar_closes_at": "2026-07-21T13:30:00-04:00",
      "minutes_to_next_15m": 15,
      "continuity": "4/5",
      "invalidated_by_opposite": false,
      "decision": {
        "passed": true,
        "score": 26,
        "runway_r": 8.72,
        "nearest_r": 6.78,
        "rungs": [
          {
            "tf": "2H",
            "level": 71.66,
            "r": 6.39,
            "gating": false
          },
          {
            "tf": "1D",
            "level": 71.59,
            "r": 6.78,
            "gating": true
          },
          {
            "tf": "1W",
            "level": 71.24,
            "r": 8.72,
            "gating": true
          }
        ],
        "continuity": {
          "4H": true,
          "1D": true
        },
        "ftfc": {
          "1H": true,
          "2H": true,
          "4H": true,
          "1D": true,
          "1W": true
        },
        "ftfc_aligned": 5,
        "nested_tfs": [
          "4H"
        ],
        "compressed": true,
        "reasons": [
          "pass: 2 gating rungs, nearest 6.8R, runway 8.7R, score 26"
        ]
      }
    },
    {
      "symbol": "AAPL",
      "setup_tf": "1D",
      "family": "f2",
      "pattern": "F2U",
      "direction": "bull",
      "trigger_side": "above",
      "level": 323.68,
      "invalidation": 322.22,
      "target": 328.45,
      "risk_reward": 3.27,
      "scale_level": 325.14,
      "runner_r": 3.27,
      "current_price": 328.38,
      "distance_pct": 1.454,
      "tier": "TIER2",
      "tier1_time": "2026-07-21T10:00:00-04:00",
      "tier2_time": "2026-07-21T10:00:00-04:00",
      "setup_bar_time": "2026-07-21T00:00:00-04:00",
      "setup_bar_closes_at": "2026-07-21T16:00:00-04:00",
      "minutes_to_next_15m": 15,
      "continuity": "5/5",
      "invalidated_by_opposite": false,
      "decision": {
        "passed": true,
        "score": 28,
        "runway_r": 7.75,
        "nearest_r": 6.87,
        "rungs": [
          {
            "tf": "2H",
            "level": 328.45,
            "r": 3.27,
            "gating": false
          },
          {
            "tf": "4H",
            "level": 329.76,
            "r": 4.17,
            "gating": false
          },
          {
            "tf": "1D",
            "level": 333.71,
            "r": 6.87,
            "gating": true
          },
          {
            "tf": "1W",
            "level": 334.99,
            "r": 7.75,
            "gating": true
          }
        ],
        "continuity": {
          "4H": true,
          "1D": true
        },
        "ftfc": {
          "1H": true,
          "2H": true,
          "4H": true,
          "1D": true,
          "1W": false
        },
        "ftfc_aligned": 4,
        "nested_tfs": [
          "4H",
          "1D"
        ],
        "compressed": true,
        "reasons": [
          "pass: 2 gating rungs, nearest 6.9R, runway 7.7R, score 28"
        ]
      }
    },
    {
      "symbol": "BABA",
      "setup_tf": "4H",
      "family": "inside",
      "pattern": "2-1-2",
      "direction": "bear",
      "trigger_side": "below",
      "level": 120.23,
      "invalidation": 121.76,
      "target": 117.65,
      "risk_reward": 1.69,
      "scale_level": 118.7,
      "runner_r": 1.69,
      "current_price": 118.3,
      "distance_pct": 1.609,
      "tier": "TIER2",
      "tier1_time": "2026-07-21T09:45:00-04:00",
      "tier2_time": "2026-07-21T09:45:00-04:00",
      "setup_bar_time": "2026-07-20T13:30:00-04:00",
      "setup_bar_closes_at": "2026-07-21T13:30:00-04:00",
      "minutes_to_next_15m": 15,
      "continuity": "4/5",
      "invalidated_by_opposite": false,
      "decision": {
        "passed": true,
        "score": 24,
        "runway_r": 5.88,
        "nearest_r": 5.88,
        "rungs": [
          {
            "tf": "2H",
            "level": 117.65,
            "r": 1.69,
            "gating": false
          },
          {
            "tf": "1W",
            "level": 111.23,
            "r": 5.88,
            "gating": true
          }
        ],
        "continuity": {
          "4H": true,
          "1D": true
        },
        "ftfc": {
          "1H": true,
          "2H": true,
          "4H": true,
          "1D": true,
          "1W": true
        },
        "ftfc_aligned": 5,
        "nested_tfs": [
          "4H"
        ],
        "compressed": true,
        "reasons": [
          "pass: 1 gating rungs, nearest 5.9R, runway 5.9R, score 24"
        ]
      }
    },
    {
      "symbol": "LLY",
      "setup_tf": "4H",
      "family": "f2",
      "pattern": "F2U",
      "direction": "bull",
      "trigger_side": "above",
      "level": 1144.43,
      "invalidation": 1139.0,
      "target": 1167.36,
      "risk_reward": 4.22,
      "scale_level": 1149.86,
      "runner_r": 4.22,
      "current_price": 1164.08,
      "distance_pct": 1.717,
      "tier": "TIER2",
      "tier1_time": "2026-07-21T10:00:00-04:00",
      "tier2_time": "2026-07-21T10:00:00-04:00",
      "setup_bar_time": "2026-07-21T09:30:00-04:00",
      "setup_bar_closes_at": "2026-07-21T13:30:00-04:00",
      "minutes_to_next_15m": 15,
      "continuity": "5/5",
      "invalidated_by_opposite": false,
      "decision": {
        "passed": true,
        "score": 24,
        "runway_r": 9.55,
        "nearest_r": 7.86,
        "rungs": [
          {
            "tf": "2H",
            "level": 1167.36,
            "r": 4.22,
            "gating": false
          },
          {
            "tf": "1D",
            "level": 1187.12,
            "r": 7.86,
            "gating": true
          },
          {
            "tf": "1W",
            "level": 1196.29,
            "r": 9.55,
            "gating": true
          }
        ],
        "continuity": {
          "4H": true,
          "1D": true
        },
        "ftfc": {
          "1H": true,
          "2H": true,
          "4H": true,
          "1D": true,
          "1W": false
        },
        "ftfc_aligned": 4,
        "nested_tfs": [
          "4H",
          "1D"
        ],
        "compressed": false,
        "reasons": [
          "pass: 2 gating rungs, nearest 7.9R, runway 9.6R, score 24"
        ]
      }
    },
    {
      "symbol": "LLY",
      "setup_tf": "1D",
      "family": "f2",
      "pattern": "F2U",
      "direction": "bull",
      "trigger_side": "above",
      "level": 1144.43,
      "invalidation": 1139.0,
      "target": 1167.36,
      "risk_reward": 4.22,
      "scale_level": 1149.86,
      "runner_r": 4.22,
      "current_price": 1164.08,
      "distance_pct": 1.717,
      "tier": "TIER2",
      "tier1_time": "2026-07-21T10:00:00-04:00",
      "tier2_time": "2026-07-21T10:00:00-04:00",
      "setup_bar_time": "2026-07-21T00:00:00-04:00",
      "setup_bar_closes_at": "2026-07-21T16:00:00-04:00",
      "minutes_to_next_15m": 15,
      "continuity": "5/5",
      "invalidated_by_opposite": false,
      "decision": {
        "passed": true,
        "score": 24,
        "runway_r": 9.55,
        "nearest_r": 7.86,
        "rungs": [
          {
            "tf": "2H",
            "level": 1167.36,
            "r": 4.22,
            "gating": false
          },
          {
            "tf": "1D",
            "level": 1187.12,
            "r": 7.86,
            "gating": true
          },
          {
            "tf": "1W",
            "level": 1196.29,
            "r": 9.55,
            "gating": true
          }
        ],
        "continuity": {
          "4H": true,
          "1D": true
        },
        "ftfc": {
          "1H": true,
          "2H": true,
          "4H": true,
          "1D": true,
          "1W": false
        },
        "ftfc_aligned": 4,
        "nested_tfs": [
          "4H",
          "1D"
        ],
        "compressed": false,
        "reasons": [
          "pass: 2 gating rungs, nearest 7.9R, runway 9.6R, score 24"
        ]
      }
    }
  ],
  "symbols": [
    {
      "symbol": "IWM",
      "price": 295.43,
      "scanned_at": "2026-07-21T11:30:27.387389-04:00",
      "timeframes": {
        "5Min": {
          "labels": [
            "2U",
            "2U",
            "1"
          ],
          "high": 295.46,
          "low": 295.17,
          "last_bar": "2026-07-21T11:25:00-04:00"
        },
        "15Min": {
          "labels": [
            "1",
            "3",
            "2U"
          ],
          "high": 295.53,
          "low": 295.0,
          "last_bar": "2026-07-21T11:15:00-04:00"
        },
        "30Min": {
          "labels": [
            "2U",
            "2U",
            "3"
          ],
          "high": 295.53,
          "low": 294.18,
          "last_bar": "2026-07-21T11:00:00-04:00"
        },
        "1H": {
          "labels": [
            "2D",
            "2U",
            "2U"
          ],
          "high": 295.53,
          "low": 294.18,
          "last_bar": "2026-07-21T10:30:00-04:00"
        },
        "2H": {
          "labels": [
            "1",
            "2D",
            "2U"
          ],
          "high": 295.53,
          "low": 292.68,
          "last_bar": "2026-07-21T09:30:00-04:00"
        },
        "4H": {
          "labels": [
            "1",
            "3",
            "2D"
          ],
          "high": 294.22,
          "low": 292.18,
          "last_bar": "2026-07-20T13:30:00-04:00"
        },
        "1D": {
          "labels": [
            "2U",
            "2D",
            "1"
          ],
          "high": 295.99,
          "low": 292.18,
          "last_bar": "2026-07-20T00:00:00-04:00"
        },
        "1W": {
          "labels": [
            "2U",
            "2D",
            "1"
          ],
          "high": 297.81,
          "low": 291.64,
          "last_bar": "2026-07-13T00:00:00-04:00"
        }
      },
      "rejected": [
        {
          "pattern": "2-1-2",
          "setup_tf": "1D",
          "direction": "bull",
          "level": 295.99,
          "reasons": [
            "gate2: nearest gating rung 0.5R < 2.0R (1W 297.81 (0.5R))"
          ]
        },
        {
          "pattern": "2-1-2",
          "setup_tf": "1D",
          "direction": "bear",
          "level": 292.18,
          "reasons": [
            "gate2: nearest gating rung 0.1R < 2.0R (1W 291.64 (0.1R))"
          ]
        }
      ]
    },
    {
      "symbol": "QQQ",
      "price": 708.69,
      "scanned_at": "2026-07-21T11:30:27.387201-04:00",
      "timeframes": {
        "5Min": {
          "labels": [
            "1",
            "3",
            "2U"
          ],
          "high": 708.99,
          "low": 708.46,
          "last_bar": "2026-07-21T11:25:00-04:00"
        },
        "15Min": {
          "labels": [
            "2U",
            "3",
            "2U"
          ],
          "high": 708.99,
          "low": 707.83,
          "last_bar": "2026-07-21T11:15:00-04:00"
        },
        "30Min": {
          "labels": [
            "2D",
            "2U",
            "2U"
          ],
          "high": 708.99,
          "low": 705.65,
          "last_bar": "2026-07-21T11:00:00-04:00"
        },
        "1H": {
          "labels": [
            "2D",
            "2U",
            "2U"
          ],
          "high": 708.99,
          "low": 705.2,
          "last_bar": "2026-07-21T10:30:00-04:00"
        },
        "2H": {
          "labels": [
            "1",
            "2D",
            "2U"
          ],
          "high": 708.99,
          "low": 702.8,
          "last_bar": "2026-07-21T09:30:00-04:00"
        },
        "4H": {
          "labels": [
            "1",
            "2U",
            "2D"
          ],
          "high": 701.42,
          "low": 695.51,
          "last_bar": "2026-07-20T13:30:00-04:00"
        },
        "1D": {
          "labels": [
            "2D",
            "2D",
            "2U"
          ],
          "high": 705.8,
          "low": 695.51,
          "last_bar": "2026-07-20T00:00:00-04:00"
        },
        "1W": {
          "labels": [
            "1",
            "2D",
            "2D"
          ],
          "high": 724.36,
          "low": 686.76,
          "last_bar": "2026-07-13T00:00:00-04:00"
        }
      },
      "rejected": []
    },
    {
      "symbol": "SPY",
      "price": 748.0,
      "scanned_at": "2026-07-21T11:30:27.387019-04:00",
      "timeframes": {
        "5Min": {
          "labels": [
            "2U",
            "2U",
            "2U"
          ],
          "high": 748.01,
          "low": 747.61,
          "last_bar": "2026-07-21T11:25:00-04:00"
        },
        "15Min": {
          "labels": [
            "2U",
            "3",
            "2U"
          ],
          "high": 748.01,
          "low": 747.16,
          "last_bar": "2026-07-21T11:15:00-04:00"
        },
        "30Min": {
          "labels": [
            "2U",
            "2U",
            "2U"
          ],
          "high": 748.01,
          "low": 745.83,
          "last_bar": "2026-07-21T11:00:00-04:00"
        },
        "1H": {
          "labels": [
            "1",
            "2U",
            "2U"
          ],
          "high": 748.01,
          "low": 745.77,
          "last_bar": "2026-07-21T10:30:00-04:00"
        },
        "2H": {
          "labels": [
            "2D",
            "2D",
            "2U"
          ],
          "high": 748.01,
          "low": 744.18,
          "last_bar": "2026-07-21T09:30:00-04:00"
        },
        "4H": {
          "labels": [
            "1",
            "2U",
            "2D"
          ],
          "high": 745.38,
          "low": 741.51,
          "last_bar": "2026-07-20T13:30:00-04:00"
        },
        "1D": {
          "labels": [
            "2D",
            "2D",
            "2U"
          ],
          "high": 748.73,
          "low": 741.51,
          "last_bar": "2026-07-20T00:00:00-04:00"
        },
        "1W": {
          "labels": [
            "2U",
            "2U",
            "2U"
          ],
          "high": 755.58,
          "low": 740.8,
          "last_bar": "2026-07-13T00:00:00-04:00"
        }
      },
      "rejected": []
    },
    {
      "symbol": "AAPL",
      "price": 328.38,
      "scanned_at": "2026-07-21T11:30:27.388149-04:00",
      "timeframes": {
        "5Min": {
          "labels": [
            "1",
            "3",
            "2U"
          ],
          "high": 328.45,
          "low": 327.99,
          "last_bar": "2026-07-21T11:25:00-04:00"
        },
        "15Min": {
          "labels": [
            "2U",
            "3",
            "2U"
          ],
          "high": 328.45,
          "low": 327.21,
          "last_bar": "2026-07-21T11:15:00-04:00"
        },
        "30Min": {
          "labels": [
            "2U",
            "2U",
            "3"
          ],
          "high": 328.45,
          "low": 326.1,
          "last_bar": "2026-07-21T11:00:00-04:00"
        },
        "1H": {
          "labels": [
            "2U",
            "2D",
            "2U"
          ],
          "high": 328.45,
          "low": 326.1,
          "last_bar": "2026-07-21T10:30:00-04:00"
        },
        "2H": {
          "labels": [
            "2D",
            "2U",
            "2D"
          ],
          "high": 328.45,
          "low": 322.22,
          "last_bar": "2026-07-21T09:30:00-04:00"
        },
        "4H": {
          "labels": [
            "1",
            "2D",
            "1"
          ],
          "high": 329.76,
          "low": 324.2,
          "last_bar": "2026-07-20T13:30:00-04:00"
        },
        "1D": {
          "labels": [
            "2U",
            "2U",
            "2D"
          ],
          "high": 333.71,
          "low": 323.68,
          "last_bar": "2026-07-20T00:00:00-04:00"
        },
        "1W": {
          "labels": [
            "2U",
            "2U",
            "2U"
          ],
          "high": 334.99,
          "low": 311.91,
          "last_bar": "2026-07-13T00:00:00-04:00"
        }
      },
      "rejected": [
        {
          "pattern": "2-1-2",
          "setup_tf": "4H",
          "direction": "bull",
          "level": 329.76,
          "reasons": [
            "gate2: nearest gating rung 0.7R < 2.0R (1D 333.71 (0.7R))"
          ]
        },
        {
          "pattern": "2-1-2",
          "setup_tf": "4H",
          "direction": "bear",
          "level": 324.2,
          "reasons": [
            "gate3: 4H, 1D forming bar against direction"
          ]
        }
      ]
    },
    {
      "symbol": "AMZN",
      "price": 248.0,
      "scanned_at": "2026-07-21T11:30:27.387922-04:00",
      "timeframes": {
        "5Min": {
          "labels": [
            "2U",
            "2U",
            "1"
          ],
          "high": 248.1,
          "low": 247.81,
          "last_bar": "2026-07-21T11:25:00-04:00"
        },
        "15Min": {
          "labels": [
            "2U",
            "2D",
            "2U"
          ],
          "high": 248.34,
          "low": 247.32,
          "last_bar": "2026-07-21T11:15:00-04:00"
        },
        "30Min": {
          "labels": [
            "1",
            "2U",
            "2D"
          ],
          "high": 248.34,
          "low": 246.96,
          "last_bar": "2026-07-21T11:00:00-04:00"
        },
        "1H": {
          "labels": [
            "1",
            "2D",
            "1"
          ],
          "high": 248.59,
          "low": 246.96,
          "last_bar": "2026-07-21T10:30:00-04:00"
        },
        "2H": {
          "labels": [
            "2U",
            "2D",
            "2D"
          ],
          "high": 249.36,
          "low": 246.72,
          "last_bar": "2026-07-21T09:30:00-04:00"
        },
        "4H": {
          "labels": [
            "1",
            "2U",
            "1"
          ],
          "high": 250.83,
          "low": 249.06,
          "last_bar": "2026-07-20T13:30:00-04:00"
        },
        "1D": {
          "labels": [
            "3",
            "2D",
            "2U"
          ],
          "high": 252.89,
          "low": 248.0,
          "last_bar": "2026-07-20T00:00:00-04:00"
        },
        "1W": {
          "labels": [
            "2U",
            "2U",
            "2U"
          ],
          "high": 258.08,
          "low": 243.59,
          "last_bar": "2026-07-13T00:00:00-04:00"
        }
      },
      "rejected": [
        {
          "pattern": "2-1-2",
          "setup_tf": "4H",
          "direction": "bull",
          "level": 250.83,
          "reasons": [
            "gate2: nearest gating rung 1.2R < 2.0R (1D 252.89 (1.2R))"
          ]
        }
      ]
    },
    {
      "symbol": "GOOGL",
      "price": 347.83,
      "scanned_at": "2026-07-21T11:30:27.388289-04:00",
      "timeframes": {
        "5Min": {
          "labels": [
            "2D",
            "2D",
            "2D"
          ],
          "high": 348.26,
          "low": 347.69,
          "last_bar": "2026-07-21T11:25:00-04:00"
        },
        "15Min": {
          "labels": [
            "2U",
            "3",
            "2D"
          ],
          "high": 349.0,
          "low": 347.69,
          "last_bar": "2026-07-21T11:15:00-04:00"
        },
        "30Min": {
          "labels": [
            "1",
            "2D",
            "3"
          ],
          "high": 350.47,
          "low": 347.69,
          "last_bar": "2026-07-21T11:00:00-04:00"
        },
        "1H": {
          "labels": [
            "2U",
            "2D",
            "1"
          ],
          "high": 350.47,
          "low": 347.69,
          "last_bar": "2026-07-21T10:30:00-04:00"
        },
        "2H": {
          "labels": [
            "1",
            "2D",
            "2D"
          ],
          "high": 351.32,
          "low": 347.59,
          "last_bar": "2026-07-21T09:30:00-04:00"
        },
        "4H": {
          "labels": [
            "1",
            "2U",
            "1"
          ],
          "high": 353.71,
          "low": 350.74,
          "last_bar": "2026-07-20T13:30:00-04:00"
        },
        "1D": {
          "labels": [
            "3",
            "2D",
            "2U"
          ],
          "high": 359.68,
          "low": 350.52,
          "last_bar": "2026-07-20T00:00:00-04:00"
        },
        "1W": {
          "labels": [
            "2U",
            "2U",
            "3"
          ],
          "high": 375.27,
          "low": 341.36,
          "last_bar": "2026-07-13T00:00:00-04:00"
        }
      },
      "rejected": [
        {
          "pattern": "2-1-2",
          "setup_tf": "4H",
          "direction": "bull",
          "level": 353.71,
          "reasons": [
            "gate3: 4H, 1D forming bar against direction"
          ]
        }
      ]
    },
    {
      "symbol": "META",
      "price": 647.88,
      "scanned_at": "2026-07-21T11:30:27.387785-04:00",
      "timeframes": {
        "5Min": {
          "labels": [
            "2D",
            "3",
            "1"
          ],
          "high": 647.9,
          "low": 647.08,
          "last_bar": "2026-07-21T11:25:00-04:00"
        },
        "15Min": {
          "labels": [
            "2U",
            "2D",
            "1"
          ],
          "high": 648.2,
          "low": 646.75,
          "last_bar": "2026-07-21T11:15:00-04:00"
        },
        "30Min": {
          "labels": [
            "1",
            "1",
            "2D"
          ],
          "high": 648.34,
          "low": 645.5,
          "last_bar": "2026-07-21T11:00:00-04:00"
        },
        "1H": {
          "labels": [
            "3",
            "3",
            "1"
          ],
          "high": 649.66,
          "low": 645.5,
          "last_bar": "2026-07-21T10:30:00-04:00"
        },
        "2H": {
          "labels": [
            "2U",
            "2D",
            "3"
          ],
          "high": 655.88,
          "low": 643.2,
          "last_bar": "2026-07-21T09:30:00-04:00"
        },
        "4H": {
          "labels": [
            "2U",
            "3",
            "1"
          ],
          "high": 651.03,
          "low": 645.26,
          "last_bar": "2026-07-20T13:30:00-04:00"
        },
        "1D": {
          "labels": [
            "1",
            "2D",
            "2U"
          ],
          "high": 653.3,
          "low": 636.01,
          "last_bar": "2026-07-20T00:00:00-04:00"
        },
        "1W": {
          "labels": [
            "2U",
            "2U",
            "2U"
          ],
          "high": 686.08,
          "low": 626.0,
          "last_bar": "2026-07-13T00:00:00-04:00"
        }
      },
      "rejected": [
        {
          "pattern": "3-1-2",
          "setup_tf": "4H",
          "direction": "bull",
          "level": 651.03,
          "reasons": [
            "gate3: 4H, 1D forming bar against direction"
          ]
        },
        {
          "pattern": "3-1-2",
          "setup_tf": "4H",
          "direction": "bear",
          "level": 645.26,
          "reasons": [
            "gate2: nearest gating rung 1.6R < 2.0R (1D 636.01 (1.6R))"
          ]
        },
        {
          "pattern": "F2D",
          "setup_tf": "4H",
          "direction": "bear",
          "level": 651.03,
          "reasons": [
            "gate3b: FTFC 3/5 aligned < 4"
          ]
        },
        {
          "pattern": "F2U",
          "setup_tf": "4H",
          "direction": "bull",
          "level": 645.26,
          "reasons": [
            "gate3: 4H, 1D forming bar against direction"
          ]
        },
        {
          "pattern": "F2D",
          "setup_tf": "1D",
          "direction": "bear",
          "level": 653.3,
          "reasons": [
            "gate3b: FTFC 3/5 aligned < 4"
          ]
        }
      ]
    },
    {
      "symbol": "MSFT",
      "price": 398.74,
      "scanned_at": "2026-07-21T11:30:27.392643-04:00",
      "timeframes": {
        "5Min": {
          "labels": [
            "2D",
            "2U",
            "2D"
          ],
          "high": 398.86,
          "low": 398.22,
          "last_bar": "2026-07-21T11:25:00-04:00"
        },
        "15Min": {
          "labels": [
            "2D",
            "2D",
            "2D"
          ],
          "high": 399.2,
          "low": 398.05,
          "last_bar": "2026-07-21T11:15:00-04:00"
        },
        "30Min": {
          "labels": [
            "1",
            "1",
            "2D"
          ],
          "high": 399.36,
          "low": 398.05,
          "last_bar": "2026-07-21T11:00:00-04:00"
        },
        "1H": {
          "labels": [
            "2U",
            "2D",
            "1"
          ],
          "high": 401.32,
          "low": 398.05,
          "last_bar": "2026-07-21T10:30:00-04:00"
        },
        "2H": {
          "labels": [
            "2U",
            "1",
            "2D"
          ],
          "high": 401.47,
          "low": 396.32,
          "last_bar": "2026-07-21T09:30:00-04:00"
        },
        "4H": {
          "labels": [
            "1",
            "3",
            "1"
          ],
          "high": 402.68,
          "low": 399.84,
          "last_bar": "2026-07-20T13:30:00-04:00"
        },
        "1D": {
          "labels": [
            "2U",
            "2D",
            "2U"
          ],
          "high": 403.18,
          "low": 389.65,
          "last_bar": "2026-07-20T00:00:00-04:00"
        },
        "1W": {
          "labels": [
            "2U",
            "2U",
            "2U"
          ],
          "high": 405.99,
          "low": 378.65,
          "last_bar": "2026-07-13T00:00:00-04:00"
        }
      },
      "rejected": [
        {
          "pattern": "3-1-2",
          "setup_tf": "4H",
          "direction": "bull",
          "level": 402.68,
          "reasons": [
            "gate2: nearest gating rung 0.2R < 2.0R (1D 403.18 (0.2R))"
          ]
        }
      ]
    },
    {
      "symbol": "NVDA",
      "price": 206.6,
      "scanned_at": "2026-07-21T11:30:30.977904-04:00",
      "timeframes": {
        "5Min": {
          "labels": [
            "1",
            "3",
            "2U"
          ],
          "high": 206.73,
          "low": 206.43,
          "last_bar": "2026-07-21T11:25:00-04:00"
        },
        "15Min": {
          "labels": [
            "2U",
            "2U",
            "2U"
          ],
          "high": 206.73,
          "low": 205.7,
          "last_bar": "2026-07-21T11:15:00-04:00"
        },
        "30Min": {
          "labels": [
            "2D",
            "1",
            "2U"
          ],
          "high": 206.73,
          "low": 205.46,
          "last_bar": "2026-07-21T11:00:00-04:00"
        },
        "1H": {
          "labels": [
            "1",
            "2U",
            "1"
          ],
          "high": 206.73,
          "low": 204.7,
          "last_bar": "2026-07-21T10:30:00-04:00"
        },
        "2H": {
          "labels": [
            "2D",
            "2D",
            "2U"
          ],
          "high": 208.65,
          "low": 204.01,
          "last_bar": "2026-07-21T09:30:00-04:00"
        },
        "4H": {
          "labels": [
            "1",
            "2U",
            "2D"
          ],
          "high": 205.01,
          "low": 202.28,
          "last_bar": "2026-07-20T13:30:00-04:00"
        },
        "1D": {
          "labels": [
            "2D",
            "2D",
            "2U"
          ],
          "high": 207.74,
          "low": 202.28,
          "last_bar": "2026-07-20T00:00:00-04:00"
        },
        "1W": {
          "labels": [
            "2D",
            "2U",
            "2U"
          ],
          "high": 213.81,
          "low": 197.97,
          "last_bar": "2026-07-13T00:00:00-04:00"
        }
      },
      "rejected": [
        {
          "pattern": "F2D",
          "setup_tf": "1D",
          "direction": "bear",
          "level": 207.74,
          "reasons": [
            "gate3b: FTFC 3/5 aligned < 4"
          ]
        }
      ]
    },
    {
      "symbol": "AVGO",
      "price": 385.66,
      "scanned_at": "2026-07-21T11:30:31.959532-04:00",
      "timeframes": {
        "5Min": {
          "labels": [
            "2D",
            "2D",
            "2U"
          ],
          "high": 386.77,
          "low": 385.6,
          "last_bar": "2026-07-21T11:25:00-04:00"
        },
        "15Min": {
          "labels": [
            "2U",
            "3",
            "2U"
          ],
          "high": 386.77,
          "low": 384.75,
          "last_bar": "2026-07-21T11:15:00-04:00"
        },
        "30Min": {
          "labels": [
            "1",
            "2U",
            "3"
          ],
          "high": 386.77,
          "low": 382.57,
          "last_bar": "2026-07-21T11:00:00-04:00"
        },
        "1H": {
          "labels": [
            "2D",
            "2U",
            "1"
          ],
          "high": 386.77,
          "low": 382.57,
          "last_bar": "2026-07-21T10:30:00-04:00"
        },
        "2H": {
          "labels": [
            "2U",
            "2D",
            "2U"
          ],
          "high": 390.58,
          "low": 379.22,
          "last_bar": "2026-07-21T09:30:00-04:00"
        },
        "4H": {
          "labels": [
            "1",
            "2U",
            "1"
          ],
          "high": 382.41,
          "low": 377.59,
          "last_bar": "2026-07-20T13:30:00-04:00"
        },
        "1D": {
          "labels": [
            "2D",
            "2D",
            "2U"
          ],
          "high": 383.59,
          "low": 375.96,
          "last_bar": "2026-07-20T00:00:00-04:00"
        },
        "1W": {
          "labels": [
            "2D",
            "2U",
            "2D"
          ],
          "high": 399.0,
          "low": 357.8,
          "last_bar": "2026-07-13T00:00:00-04:00"
        }
      },
      "rejected": [
        {
          "pattern": "2-1-2",
          "setup_tf": "4H",
          "direction": "bull",
          "level": 382.41,
          "reasons": [
            "gate3: 4H, 1D forming bar against direction"
          ]
        },
        {
          "pattern": "2-1-2",
          "setup_tf": "4H",
          "direction": "bear",
          "level": 377.59,
          "reasons": [
            "gate2: nearest gating rung 0.3R < 2.0R (1D 375.96 (0.3R))"
          ]
        }
      ]
    },
    {
      "symbol": "PLTR",
      "price": 133.17,
      "scanned_at": "2026-07-21T11:30:37.581090-04:00",
      "timeframes": {
        "5Min": {
          "labels": [
            "3",
            "2U",
            "2D"
          ],
          "high": 133.48,
          "low": 133.05,
          "last_bar": "2026-07-21T11:25:00-04:00"
        },
        "15Min": {
          "labels": [
            "1",
            "2D",
            "2D"
          ],
          "high": 133.73,
          "low": 132.76,
          "last_bar": "2026-07-21T11:15:00-04:00"
        },
        "30Min": {
          "labels": [
            "1",
            "1",
            "2D"
          ],
          "high": 133.9,
          "low": 132.76,
          "last_bar": "2026-07-21T11:00:00-04:00"
        },
        "1H": {
          "labels": [
            "2D",
            "2D",
            "1"
          ],
          "high": 134.57,
          "low": 132.76,
          "last_bar": "2026-07-21T10:30:00-04:00"
        },
        "2H": {
          "labels": [
            "2U",
            "2U",
            "2D"
          ],
          "high": 134.68,
          "low": 131.22,
          "last_bar": "2026-07-21T09:30:00-04:00"
        },
        "4H": {
          "labels": [
            "2U",
            "2U",
            "2U"
          ],
          "high": 136.62,
          "low": 134.82,
          "last_bar": "2026-07-20T13:30:00-04:00"
        },
        "1D": {
          "labels": [
            "2D",
            "1",
            "2U"
          ],
          "high": 136.62,
          "low": 131.82,
          "last_bar": "2026-07-20T00:00:00-04:00"
        },
        "1W": {
          "labels": [
            "2U",
            "2U",
            "2D"
          ],
          "high": 136.88,
          "low": 122.64,
          "last_bar": "2026-07-13T00:00:00-04:00"
        }
      },
      "rejected": [
        {
          "pattern": "F2U",
          "setup_tf": "1D",
          "direction": "bull",
          "level": 131.82,
          "reasons": [
            "gate3: 4H, 1D forming bar against direction"
          ]
        }
      ]
    },
    {
      "symbol": "TSLA",
      "price": 381.91,
      "scanned_at": "2026-07-21T11:30:40.210142-04:00",
      "timeframes": {
        "5Min": {
          "labels": [
            "2D",
            "2D",
            "1"
          ],
          "high": 382.06,
          "low": 381.06,
          "last_bar": "2026-07-21T11:25:00-04:00"
        },
        "15Min": {
          "labels": [
            "2U",
            "2D",
            "2D"
          ],
          "high": 382.46,
          "low": 380.95,
          "last_bar": "2026-07-21T11:15:00-04:00"
        },
        "30Min": {
          "labels": [
            "2U",
            "2U",
            "2D"
          ],
          "high": 382.98,
          "low": 380.95,
          "last_bar": "2026-07-21T11:00:00-04:00"
        },
        "1H": {
          "labels": [
            "2D",
            "2U",
            "2U"
          ],
          "high": 384.07,
          "low": 380.95,
          "last_bar": "2026-07-21T10:30:00-04:00"
        },
        "2H": {
          "labels": [
            "2D",
            "2D",
            "2U"
          ],
          "high": 384.07,
          "low": 369.98,
          "last_bar": "2026-07-21T09:30:00-04:00"
        },
        "4H": {
          "labels": [
            "1",
            "3",
            "2D"
          ],
          "high": 374.6,
          "low": 369.43,
          "last_bar": "2026-07-20T13:30:00-04:00"
        },
        "1D": {
          "labels": [
            "2D",
            "2D",
            "3"
          ],
          "high": 386.61,
          "low": 369.43,
          "last_bar": "2026-07-20T00:00:00-04:00"
        },
        "1W": {
          "labels": [
            "2U",
            "1",
            "2D"
          ],
          "high": 406.59,
          "low": 377.22,
          "last_bar": "2026-07-13T00:00:00-04:00"
        }
      },
      "rejected": []
    },
    {
      "symbol": "MSTR",
      "price": 102.48,
      "scanned_at": "2026-07-21T11:30:40.899212-04:00",
      "timeframes": {
        "5Min": {
          "labels": [
            "3",
            "2U",
            "2D"
          ],
          "high": 103.1,
          "low": 102.45,
          "last_bar": "2026-07-21T11:25:00-04:00"
        },
        "15Min": {
          "labels": [
            "2U",
            "2D",
            "2U"
          ],
          "high": 103.6,
          "low": 102.45,
          "last_bar": "2026-07-21T11:15:00-04:00"
        },
        "30Min": {
          "labels": [
            "2U",
            "2D",
            "3"
          ],
          "high": 103.6,
          "low": 102.07,
          "last_bar": "2026-07-21T11:00:00-04:00"
        },
        "1H": {
          "labels": [
            "1",
            "2U",
            "1"
          ],
          "high": 103.6,
          "low": 102.07,
          "last_bar": "2026-07-21T10:30:00-04:00"
        },
        "2H": {
          "labels": [
            "2U",
            "3",
            "2U"
          ],
          "high": 104.6,
          "low": 100.31,
          "last_bar": "2026-07-21T09:30:00-04:00"
        },
        "4H": {
          "labels": [
            "1",
            "2U",
            "2U"
          ],
          "high": 100.92,
          "low": 96.96,
          "last_bar": "2026-07-20T13:30:00-04:00"
        },
        "1D": {
          "labels": [
            "2D",
            "2D",
            "2U"
          ],
          "high": 100.92,
          "low": 94.86,
          "last_bar": "2026-07-20T00:00:00-04:00"
        },
        "1W": {
          "labels": [
            "1",
            "2U",
            "2D"
          ],
          "high": 101.95,
          "low": 90.02,
          "last_bar": "2026-07-13T00:00:00-04:00"
        }
      },
      "rejected": []
    },
    {
      "symbol": "MU",
      "price": 953.61,
      "scanned_at": "2026-07-21T11:30:44.133552-04:00",
      "timeframes": {
        "5Min": {
          "labels": [
            "2U",
            "2D",
            "2U"
          ],
          "high": 958.5,
          "low": 954.13,
          "last_bar": "2026-07-21T11:25:00-04:00"
        },
        "15Min": {
          "labels": [
            "2U",
            "2U",
            "2U"
          ],
          "high": 958.5,
          "low": 951.41,
          "last_bar": "2026-07-21T11:15:00-04:00"
        },
        "30Min": {
          "labels": [
            "2D",
            "2U",
            "2U"
          ],
          "high": 958.5,
          "low": 944.96,
          "last_bar": "2026-07-21T11:00:00-04:00"
        },
        "1H": {
          "labels": [
            "1",
            "2U",
            "2U"
          ],
          "high": 958.5,
          "low": 927.21,
          "last_bar": "2026-07-21T10:30:00-04:00"
        },
        "2H": {
          "labels": [
            "2U",
            "2D",
            "2U"
          ],
          "high": 958.5,
          "low": 916.57,
          "last_bar": "2026-07-21T09:30:00-04:00"
        },
        "4H": {
          "labels": [
            "1",
            "2U",
            "2D"
          ],
          "high": 889.87,
          "low": 858.9,
          "last_bar": "2026-07-20T13:30:00-04:00"
        },
        "1D": {
          "labels": [
            "2D",
            "3",
            "1"
          ],
          "high": 901.0,
          "low": 858.9,
          "last_bar": "2026-07-20T00:00:00-04:00"
        },
        "1W": {
          "labels": [
            "2D",
            "2D",
            "2D"
          ],
          "high": 994.8,
          "low": 804.0,
          "last_bar": "2026-07-13T00:00:00-04:00"
        }
      },
      "rejected": [
        {
          "pattern": "3-1-2",
          "setup_tf": "1D",
          "direction": "bull",
          "level": 901.0,
          "reasons": [
            "gate3b: FTFC 3/5 aligned < 4"
          ]
        },
        {
          "pattern": "3-1-2",
          "setup_tf": "1D",
          "direction": "bear",
          "level": 858.9,
          "reasons": [
            "gate2: nearest gating rung 1.3R < 2.0R (1W 804.00 (1.3R))"
          ]
        }
      ]
    },
    {
      "symbol": "ORCL",
      "price": 125.27,
      "scanned_at": "2026-07-21T11:30:44.702417-04:00",
      "timeframes": {
        "5Min": {
          "labels": [
            "3",
            "2U",
            "2U"
          ],
          "high": 125.65,
          "low": 125.19,
          "last_bar": "2026-07-21T11:25:00-04:00"
        },
        "15Min": {
          "labels": [
            "1",
            "2D",
            "2U"
          ],
          "high": 125.65,
          "low": 124.87,
          "last_bar": "2026-07-21T11:15:00-04:00"
        },
        "30Min": {
          "labels": [
            "2U",
            "1",
            "2D"
          ],
          "high": 125.65,
          "low": 124.53,
          "last_bar": "2026-07-21T11:00:00-04:00"
        },
        "1H": {
          "labels": [
            "2D",
            "2U",
            "1"
          ],
          "high": 125.83,
          "low": 124.53,
          "last_bar": "2026-07-21T10:30:00-04:00"
        },
        "2H": {
          "labels": [
            "1",
            "3",
            "2U"
          ],
          "high": 126.21,
          "low": 122.21,
          "last_bar": "2026-07-21T09:30:00-04:00"
        },
        "4H": {
          "labels": [
            "1",
            "2D",
            "1"
          ],
          "high": 123.88,
          "low": 121.28,
          "last_bar": "2026-07-20T13:30:00-04:00"
        },
        "1D": {
          "labels": [
            "2D",
            "2D",
            "2D"
          ],
          "high": 125.49,
          "low": 120.03,
          "last_bar": "2026-07-20T00:00:00-04:00"
        },
        "1W": {
          "labels": [
            "2D",
            "2D",
            "2D"
          ],
          "high": 139.65,
          "low": 121.5,
          "last_bar": "2026-07-13T00:00:00-04:00"
        }
      },
      "rejected": [
        {
          "pattern": "2-1-2",
          "setup_tf": "4H",
          "direction": "bear",
          "level": 121.28,
          "reasons": [
            "gate2: nearest gating rung 0.5R < 2.0R (1D 120.03 (0.5R))"
          ]
        },
        {
          "pattern": "F2D",
          "setup_tf": "1D",
          "direction": "bear",
          "level": 125.49,
          "reasons": [
            "gate3: 4H, 1D forming bar against direction"
          ]
        }
      ]
    },
    {
      "symbol": "NBIS",
      "price": 207.02,
      "scanned_at": "2026-07-21T11:30:44.847474-04:00",
      "timeframes": {
        "5Min": {
          "labels": [
            "2D",
            "2D",
            "2U"
          ],
          "high": 207.6,
          "low": 206.78,
          "last_bar": "2026-07-21T11:25:00-04:00"
        },
        "15Min": {
          "labels": [
            "1",
            "2U",
            "1"
          ],
          "high": 207.6,
          "low": 206.0,
          "last_bar": "2026-07-21T11:15:00-04:00"
        },
        "30Min": {
          "labels": [
            "2U",
            "2U",
            "2U"
          ],
          "high": 208.25,
          "low": 205.01,
          "last_bar": "2026-07-21T11:00:00-04:00"
        },
        "1H": {
          "labels": [
            "1",
            "2U",
            "2U"
          ],
          "high": 208.25,
          "low": 204.06,
          "last_bar": "2026-07-21T10:30:00-04:00"
        },
        "2H": {
          "labels": [
            "1",
            "2D",
            "2U"
          ],
          "high": 208.25,
          "low": 192.12,
          "last_bar": "2026-07-21T09:30:00-04:00"
        },
        "4H": {
          "labels": [
            "2U",
            "2U",
            "2D"
          ],
          "high": 188.25,
          "low": 179.08,
          "last_bar": "2026-07-20T13:30:00-04:00"
        },
        "1D": {
          "labels": [
            "2D",
            "2D",
            "2U"
          ],
          "high": 194.34,
          "low": 179.08,
          "last_bar": "2026-07-20T00:00:00-04:00"
        },
        "1W": {
          "labels": [
            "2D",
            "2D",
            "2D"
          ],
          "high": 222.75,
          "low": 164.31,
          "last_bar": "2026-07-13T00:00:00-04:00"
        }
      },
      "rejected": []
    },
    {
      "symbol": "JPM",
      "price": 343.08,
      "scanned_at": "2026-07-21T11:30:45.466263-04:00",
      "timeframes": {
        "5Min": {
          "labels": [
            "2U",
            "3",
            "2D"
          ],
          "high": 343.22,
          "low": 342.35,
          "last_bar": "2026-07-21T11:25:00-04:00"
        },
        "15Min": {
          "labels": [
            "1",
            "2U",
            "2U"
          ],
          "high": 343.83,
          "low": 342.35,
          "last_bar": "2026-07-21T11:15:00-04:00"
        },
        "30Min": {
          "labels": [
            "2U",
            "1",
            "2U"
          ],
          "high": 343.83,
          "low": 342.23,
          "last_bar": "2026-07-21T11:00:00-04:00"
        },
        "1H": {
          "labels": [
            "1",
            "3",
            "2U"
          ],
          "high": 343.83,
          "low": 342.02,
          "last_bar": "2026-07-21T10:30:00-04:00"
        },
        "2H": {
          "labels": [
            "1",
            "2D",
            "3"
          ],
          "high": 343.83,
          "low": 337.3,
          "last_bar": "2026-07-21T09:30:00-04:00"
        },
        "4H": {
          "labels": [
            "1",
            "2D",
            "2D"
          ],
          "high": 339.6,
          "low": 337.37,
          "last_bar": "2026-07-20T13:30:00-04:00"
        },
        "1D": {
          "labels": [
            "2D",
            "2D",
            "1"
          ],
          "high": 344.26,
          "low": 337.37,
          "last_bar": "2026-07-20T00:00:00-04:00"
        },
        "1W": {
          "labels": [
            "2D",
            "2U",
            "3"
          ],
          "high": 351.24,
          "low": 325.75,
          "last_bar": "2026-07-13T00:00:00-04:00"
        }
      },
      "rejected": [
        {
          "pattern": "F2U",
          "setup_tf": "4H",
          "direction": "bull",
          "level": 337.37,
          "reasons": [
            "gate2a: risk 0.07 is 0.021% of price (< 0.15%) -- stop is inside the noise"
          ]
        },
        {
          "pattern": "2-1-2",
          "setup_tf": "1D",
          "direction": "bull",
          "level": 344.26,
          "reasons": [
            "gate2: nearest gating rung 1.0R < 2.0R (1W 351.24 (1.0R))"
          ]
        },
        {
          "pattern": "2-1-2",
          "setup_tf": "1D",
          "direction": "bear",
          "level": 337.37,
          "reasons": [
            "gate2: nearest gating rung 1.7R < 2.0R (1W 325.75 (1.7R))"
          ]
        },
        {
          "pattern": "F2U",
          "setup_tf": "1D",
          "direction": "bull",
          "level": 337.37,
          "reasons": [
            "gate2a: risk 0.07 is 0.021% of price (< 0.15%) -- stop is inside the noise"
          ]
        }
      ]
    },
    {
      "symbol": "BABA",
      "price": 118.3,
      "scanned_at": "2026-07-21T11:30:46.237524-04:00",
      "timeframes": {
        "5Min": {
          "labels": [
            "2D",
            "2U",
            "2U"
          ],
          "high": 118.31,
          "low": 118.14,
          "last_bar": "2026-07-21T11:25:00-04:00"
        },
        "15Min": {
          "labels": [
            "2D",
            "1",
            "2U"
          ],
          "high": 118.31,
          "low": 117.95,
          "last_bar": "2026-07-21T11:15:00-04:00"
        },
        "30Min": {
          "labels": [
            "2D",
            "1",
            "1"
          ],
          "high": 118.31,
          "low": 117.85,
          "last_bar": "2026-07-21T11:00:00-04:00"
        },
        "1H": {
          "labels": [
            "2D",
            "2D",
            "1"
          ],
          "high": 118.64,
          "low": 117.82,
          "last_bar": "2026-07-21T10:30:00-04:00"
        },
        "2H": {
          "labels": [
            "2U",
            "1",
            "2D"
          ],
          "high": 119.45,
          "low": 117.65,
          "last_bar": "2026-07-21T09:30:00-04:00"
        },
        "4H": {
          "labels": [
            "1",
            "2U",
            "1"
          ],
          "high": 121.76,
          "low": 120.23,
          "last_bar": "2026-07-20T13:30:00-04:00"
        },
        "1D": {
          "labels": [
            "1",
            "2D",
            "2U"
          ],
          "high": 121.86,
          "low": 117.86,
          "last_bar": "2026-07-20T00:00:00-04:00"
        },
        "1W": {
          "labels": [
            "1",
            "2U",
            "2U"
          ],
          "high": 121.22,
          "low": 111.23,
          "last_bar": "2026-07-13T00:00:00-04:00"
        }
      },
      "rejected": [
        {
          "pattern": "2-1-2",
          "setup_tf": "4H",
          "direction": "bull",
          "level": 121.76,
          "reasons": [
            "gate2: nearest gating rung 0.1R < 2.0R (1D 121.86 (0.1R))"
          ]
        },
        {
          "pattern": "F2U",
          "setup_tf": "1D",
          "direction": "bull",
          "level": 117.86,
          "reasons": [
            "gate3: 4H, 1D forming bar against direction"
          ]
        }
      ]
    },
    {
      "symbol": "COST",
      "price": 930.2,
      "scanned_at": "2026-07-21T11:30:51.313425-04:00",
      "timeframes": {
        "5Min": {
          "labels": [
            "3",
            "2U",
            "2D"
          ],
          "high": 931.05,
          "low": 929.14,
          "last_bar": "2026-07-21T11:25:00-04:00"
        },
        "15Min": {
          "labels": [
            "3",
            "2U",
            "3"
          ],
          "high": 931.99,
          "low": 927.65,
          "last_bar": "2026-07-21T11:15:00-04:00"
        },
        "30Min": {
          "labels": [
            "1",
            "1",
            "2U"
          ],
          "high": 931.99,
          "low": 927.65,
          "last_bar": "2026-07-21T11:00:00-04:00"
        },
        "1H": {
          "labels": [
            "2U",
            "2D",
            "2U"
          ],
          "high": 931.99,
          "low": 926.26,
          "last_bar": "2026-07-21T10:30:00-04:00"
        },
        "2H": {
          "labels": [
            "1",
            "2D",
            "2D"
          ],
          "high": 931.99,
          "low": 924.44,
          "last_bar": "2026-07-21T09:30:00-04:00"
        },
        "4H": {
          "labels": [
            "1",
            "2U",
            "2D"
          ],
          "high": 938.59,
          "low": 932.01,
          "last_bar": "2026-07-20T13:30:00-04:00"
        },
        "1D": {
          "labels": [
            "2U",
            "2U",
            "2D"
          ],
          "high": 946.98,
          "low": 932.01,
          "last_bar": "2026-07-20T00:00:00-04:00"
        },
        "1W": {
          "labels": [
            "3",
            "2D",
            "1"
          ],
          "high": 964.33,
          "low": 910.5,
          "last_bar": "2026-07-13T00:00:00-04:00"
        }
      },
      "rejected": []
    },
    {
      "symbol": "NFLX",
      "price": 67.47,
      "scanned_at": "2026-07-21T11:30:52.218254-04:00",
      "timeframes": {
        "5Min": {
          "labels": [
            "2D",
            "3",
            "2D"
          ],
          "high": 67.63,
          "low": 67.44,
          "last_bar": "2026-07-21T11:25:00-04:00"
        },
        "15Min": {
          "labels": [
            "2U",
            "1",
            "2D"
          ],
          "high": 67.78,
          "low": 67.44,
          "last_bar": "2026-07-21T11:15:00-04:00"
        },
        "30Min": {
          "labels": [
            "2U",
            "2D",
            "2D"
          ],
          "high": 67.99,
          "low": 67.44,
          "last_bar": "2026-07-21T11:00:00-04:00"
        },
        "1H": {
          "labels": [
            "2U",
            "3",
            "1"
          ],
          "high": 68.02,
          "low": 67.44,
          "last_bar": "2026-07-21T10:30:00-04:00"
        },
        "2H": {
          "labels": [
            "1",
            "2D",
            "2U"
          ],
          "high": 68.1,
          "low": 67.16,
          "last_bar": "2026-07-21T09:30:00-04:00"
        },
        "4H": {
          "labels": [
            "2U",
            "2D",
            "1"
          ],
          "high": 67.84,
          "low": 67.08,
          "last_bar": "2026-07-20T13:30:00-04:00"
        },
        "1D": {
          "labels": [
            "2D",
            "2D",
            "1"
          ],
          "high": 68.38,
          "low": 66.69,
          "last_bar": "2026-07-20T00:00:00-04:00"
        },
        "1W": {
          "labels": [
            "2U",
            "1",
            "2D"
          ],
          "high": 75.45,
          "low": 65.08,
          "last_bar": "2026-07-13T00:00:00-04:00"
        }
      },
      "rejected": [
        {
          "pattern": "2-1-2",
          "setup_tf": "4H",
          "direction": "bull",
          "level": 67.84,
          "reasons": [
            "gate2: nearest gating rung 0.7R < 2.0R (1D 68.38 (0.7R))"
          ]
        },
        {
          "pattern": "2-1-2",
          "setup_tf": "4H",
          "direction": "bear",
          "level": 67.08,
          "reasons": [
            "gate2: nearest gating rung 0.5R < 2.0R (1D 66.69 (0.5R))"
          ]
        },
        {
          "pattern": "F2D",
          "setup_tf": "4H",
          "direction": "bear",
          "level": 67.84,
          "reasons": [
            "gate3: 4H, 1D forming bar against direction"
          ]
        },
        {
          "pattern": "2-1-2",
          "setup_tf": "1D",
          "direction": "bull",
          "level": 68.38,
          "reasons": [
            "gate3b: FTFC 3/5 aligned < 4"
          ]
        },
        {
          "pattern": "2-1-2",
          "setup_tf": "1D",
          "direction": "bear",
          "level": 66.69,
          "reasons": [
            "gate2: nearest gating rung 1.0R < 2.0R (1W 65.08 (1.0R))"
          ]
        }
      ]
    },
    {
      "symbol": "UBER",
      "price": 71.85,
      "scanned_at": "2026-07-21T11:30:53.286719-04:00",
      "timeframes": {
        "5Min": {
          "labels": [
            "2U",
            "2U",
            "2U"
          ],
          "high": 71.99,
          "low": 71.83,
          "last_bar": "2026-07-21T11:25:00-04:00"
        },
        "15Min": {
          "labels": [
            "1",
            "2D",
            "2U"
          ],
          "high": 71.99,
          "low": 71.7,
          "last_bar": "2026-07-21T11:15:00-04:00"
        },
        "30Min": {
          "labels": [
            "2D",
            "1",
            "2D"
          ],
          "high": 71.99,
          "low": 71.66,
          "last_bar": "2026-07-21T11:00:00-04:00"
        },
        "1H": {
          "labels": [
            "2U",
            "3",
            "2D"
          ],
          "high": 72.0,
          "low": 71.66,
          "last_bar": "2026-07-21T10:30:00-04:00"
        },
        "2H": {
          "labels": [
            "2U",
            "2D",
            "3"
          ],
          "high": 72.99,
          "low": 71.66,
          "last_bar": "2026-07-21T09:30:00-04:00"
        },
        "4H": {
          "labels": [
            "1",
            "3",
            "1"
          ],
          "high": 72.81,
          "low": 71.93,
          "last_bar": "2026-07-20T13:30:00-04:00"
        },
        "1D": {
          "labels": [
            "2U",
            "2D",
            "2D"
          ],
          "high": 73.41,
          "low": 71.59,
          "last_bar": "2026-07-20T00:00:00-04:00"
        },
        "1W": {
          "labels": [
            "2U",
            "1",
            "3"
          ],
          "high": 76.3,
          "low": 71.24,
          "last_bar": "2026-07-13T00:00:00-04:00"
        }
      },
      "rejected": [
        {
          "pattern": "3-1-2",
          "setup_tf": "4H",
          "direction": "bull",
          "level": 72.81,
          "reasons": [
            "gate2: nearest gating rung 0.7R < 2.0R (1D 73.41 (0.7R))"
          ]
        },
        {
          "pattern": "3-1-2",
          "setup_tf": "4H",
          "direction": "bear",
          "level": 71.93,
          "reasons": [
            "gate2: nearest gating rung 0.4R < 2.0R (1D 71.59 (0.4R))"
          ]
        }
      ]
    },
    {
      "symbol": "LLY",
      "price": 1164.08,
      "scanned_at": "2026-07-21T11:30:54.706419-04:00",
      "timeframes": {
        "5Min": {
          "labels": [
            "1",
            "2D",
            "3"
          ],
          "high": 1164.45,
          "low": 1161.33,
          "last_bar": "2026-07-21T11:25:00-04:00"
        },
        "15Min": {
          "labels": [
            "2U",
            "1",
            "1"
          ],
          "high": 1164.45,
          "low": 1161.33,
          "last_bar": "2026-07-21T11:15:00-04:00"
        },
        "30Min": {
          "labels": [
            "2U",
            "1",
            "1"
          ],
          "high": 1164.71,
          "low": 1158.95,
          "last_bar": "2026-07-21T11:00:00-04:00"
        },
        "1H": {
          "labels": [
            "2D",
            "3",
            "1"
          ],
          "high": 1165.03,
          "low": 1157.57,
          "last_bar": "2026-07-21T10:30:00-04:00"
        },
        "2H": {
          "labels": [
            "2D",
            "2D",
            "3"
          ],
          "high": 1167.36,
          "low": 1139.0,
          "last_bar": "2026-07-21T09:30:00-04:00"
        },
        "4H": {
          "labels": [
            "1",
            "3",
            "2D"
          ],
          "high": 1164.05,
          "low": 1144.43,
          "last_bar": "2026-07-20T13:30:00-04:00"
        },
        "1D": {
          "labels": [
            "2U",
            "1",
            "2D"
          ],
          "high": 1187.12,
          "low": 1144.43,
          "last_bar": "2026-07-20T00:00:00-04:00"
        },
        "1W": {
          "labels": [
            "2U",
            "2U",
            "2D"
          ],
          "high": 1196.29,
          "low": 1134.4,
          "last_bar": "2026-07-13T00:00:00-04:00"
        }
      },
      "rejected": []
    },
    {
      "symbol": "CAT",
      "price": 887.73,
      "scanned_at": "2026-07-21T11:30:57.600181-04:00",
      "timeframes": {
        "5Min": {
          "labels": [
            "2U",
            "2D",
            "2U"
          ],
          "high": 890.0,
          "low": 888.3,
          "last_bar": "2026-07-21T11:25:00-04:00"
        },
        "15Min": {
          "labels": [
            "1",
            "2U",
            "2U"
          ],
          "high": 890.0,
          "low": 887.93,
          "last_bar": "2026-07-21T11:15:00-04:00"
        },
        "30Min": {
          "labels": [
            "1",
            "2U",
            "2U"
          ],
          "high": 890.0,
          "low": 885.45,
          "last_bar": "2026-07-21T11:00:00-04:00"
        },
        "1H": {
          "labels": [
            "1",
            "2U",
            "1"
          ],
          "high": 890.0,
          "low": 883.86,
          "last_bar": "2026-07-21T10:30:00-04:00"
        },
        "2H": {
          "labels": [
            "2D",
            "2D",
            "2U"
          ],
          "high": 894.0,
          "low": 876.01,
          "last_bar": "2026-07-21T09:30:00-04:00"
        },
        "4H": {
          "labels": [
            "1",
            "3",
            "2D"
          ],
          "high": 868.99,
          "low": 861.27,
          "last_bar": "2026-07-20T13:30:00-04:00"
        },
        "1D": {
          "labels": [
            "2D",
            "2D",
            "2U"
          ],
          "high": 894.37,
          "low": 861.27,
          "last_bar": "2026-07-20T00:00:00-04:00"
        },
        "1W": {
          "labels": [
            "3",
            "2D",
            "2D"
          ],
          "high": 964.63,
          "low": 838.33,
          "last_bar": "2026-07-13T00:00:00-04:00"
        }
      },
      "rejected": []
    },
    {
      "symbol": "XOM",
      "price": 151.25,
      "scanned_at": "2026-07-21T11:30:59.716359-04:00",
      "timeframes": {
        "5Min": {
          "labels": [
            "3",
            "3",
            "2U"
          ],
          "high": 151.33,
          "low": 151.09,
          "last_bar": "2026-07-21T11:25:00-04:00"
        },
        "15Min": {
          "labels": [
            "3",
            "2U",
            "3"
          ],
          "high": 151.33,
          "low": 150.69,
          "last_bar": "2026-07-21T11:15:00-04:00"
        },
        "30Min": {
          "labels": [
            "1",
            "2U",
            "2U"
          ],
          "high": 151.33,
          "low": 150.69,
          "last_bar": "2026-07-21T11:00:00-04:00"
        },
        "1H": {
          "labels": [
            "2D",
            "2U",
            "2U"
          ],
          "high": 151.33,
          "low": 150.3,
          "last_bar": "2026-07-21T10:30:00-04:00"
        },
        "2H": {
          "labels": [
            "2U",
            "3",
            "2U"
          ],
          "high": 151.33,
          "low": 148.48,
          "last_bar": "2026-07-21T09:30:00-04:00"
        },
        "4H": {
          "labels": [
            "2D",
            "3",
            "2U"
          ],
          "high": 149.09,
          "low": 148.29,
          "last_bar": "2026-07-20T13:30:00-04:00"
        },
        "1D": {
          "labels": [
            "2U",
            "2U",
            "2D"
          ],
          "high": 149.09,
          "low": 146.23,
          "last_bar": "2026-07-20T00:00:00-04:00"
        },
        "1W": {
          "labels": [
            "1",
            "2U",
            "2U"
          ],
          "high": 150.0,
          "low": 140.49,
          "last_bar": "2026-07-13T00:00:00-04:00"
        }
      },
      "rejected": []
    },
    {
      "symbol": "IONQ",
      "price": 35.78,
      "scanned_at": "2026-07-21T11:31:01.421294-04:00",
      "timeframes": {
        "5Min": {
          "labels": [
            "1",
            "2D",
            "2U"
          ],
          "high": 35.85,
          "low": 35.7,
          "last_bar": "2026-07-21T11:25:00-04:00"
        },
        "15Min": {
          "labels": [
            "2D",
            "3",
            "2U"
          ],
          "high": 35.85,
          "low": 35.63,
          "last_bar": "2026-07-21T11:15:00-04:00"
        },
        "30Min": {
          "labels": [
            "1",
            "2U",
            "2D"
          ],
          "high": 35.85,
          "low": 35.27,
          "last_bar": "2026-07-21T11:00:00-04:00"
        },
        "1H": {
          "labels": [
            "2D",
            "2U",
            "1"
          ],
          "high": 35.91,
          "low": 35.27,
          "last_bar": "2026-07-21T10:30:00-04:00"
        },
        "2H": {
          "labels": [
            "1",
            "2D",
            "2U"
          ],
          "high": 35.93,
          "low": 34.7,
          "last_bar": "2026-07-21T09:30:00-04:00"
        },
        "4H": {
          "labels": [
            "1",
            "3",
            "2D"
          ],
          "high": 35.22,
          "low": 34.21,
          "last_bar": "2026-07-20T13:30:00-04:00"
        },
        "1D": {
          "labels": [
            "2D",
            "2D",
            "2U"
          ],
          "high": 36.3,
          "low": 34.21,
          "last_bar": "2026-07-20T00:00:00-04:00"
        },
        "1W": {
          "labels": [
            "2D",
            "2D",
            "2D"
          ],
          "high": 42.18,
          "low": 33.29,
          "last_bar": "2026-07-13T00:00:00-04:00"
        }
      },
      "rejected": []
    },
    {
      "symbol": "RIVN",
      "price": 17.68,
      "scanned_at": "2026-07-21T11:31:05.155589-04:00",
      "timeframes": {
        "5Min": {
          "labels": [
            "1",
            "3",
            "1"
          ],
          "high": 17.71,
          "low": 17.67,
          "last_bar": "2026-07-21T11:25:00-04:00"
        },
        "15Min": {
          "labels": [
            "3",
            "2U",
            "1"
          ],
          "high": 17.73,
          "low": 17.64,
          "last_bar": "2026-07-21T11:15:00-04:00"
        },
        "30Min": {
          "labels": [
            "2U",
            "2U",
            "2U"
          ],
          "high": 17.73,
          "low": 17.57,
          "last_bar": "2026-07-21T11:00:00-04:00"
        },
        "1H": {
          "labels": [
            "1",
            "2U",
            "2U"
          ],
          "high": 17.73,
          "low": 17.5,
          "last_bar": "2026-07-21T10:30:00-04:00"
        },
        "2H": {
          "labels": [
            "1",
            "2D",
            "2U"
          ],
          "high": 17.73,
          "low": 17.13,
          "last_bar": "2026-07-21T09:30:00-04:00"
        },
        "4H": {
          "labels": [
            "1",
            "2U",
            "2D"
          ],
          "high": 17.49,
          "low": 17.07,
          "last_bar": "2026-07-20T13:30:00-04:00"
        },
        "1D": {
          "labels": [
            "2D",
            "2D",
            "2U"
          ],
          "high": 17.99,
          "low": 17.07,
          "last_bar": "2026-07-20T00:00:00-04:00"
        },
        "1W": {
          "labels": [
            "2U",
            "3",
            "1"
          ],
          "high": 18.79,
          "low": 16.49,
          "last_bar": "2026-07-13T00:00:00-04:00"
        }
      },
      "rejected": []
    },
    {
      "symbol": "WDC",
      "price": 546.94,
      "scanned_at": "2026-07-21T11:31:06.388138-04:00",
      "timeframes": {
        "5Min": {
          "labels": [
            "2D",
            "2D",
            "2U"
          ],
          "high": 548.99,
          "low": 547.5,
          "last_bar": "2026-07-21T11:25:00-04:00"
        },
        "15Min": {
          "labels": [
            "2U",
            "2U",
            "1"
          ],
          "high": 549.8,
          "low": 545.71,
          "last_bar": "2026-07-21T11:15:00-04:00"
        },
        "30Min": {
          "labels": [
            "2U",
            "2U",
            "2U"
          ],
          "high": 550.83,
          "low": 544.65,
          "last_bar": "2026-07-21T11:00:00-04:00"
        },
        "1H": {
          "labels": [
            "2D",
            "2U",
            "2U"
          ],
          "high": 550.83,
          "low": 537.84,
          "last_bar": "2026-07-21T10:30:00-04:00"
        },
        "2H": {
          "labels": [
            "1",
            "2D",
            "2U"
          ],
          "high": 550.83,
          "low": 517.01,
          "last_bar": "2026-07-21T09:30:00-04:00"
        },
        "4H": {
          "labels": [
            "2U",
            "2U",
            "2D"
          ],
          "high": 499.57,
          "low": 485.28,
          "last_bar": "2026-07-20T13:30:00-04:00"
        },
        "1D": {
          "labels": [
            "2D",
            "2D",
            "2U"
          ],
          "high": 505.99,
          "low": 485.28,
          "last_bar": "2026-07-20T00:00:00-04:00"
        },
        "1W": {
          "labels": [
            "2D",
            "2D",
            "2D"
          ],
          "high": 589.65,
          "low": 430.52,
          "last_bar": "2026-07-13T00:00:00-04:00"
        }
      },
      "rejected": []
    },
    {
      "symbol": "RKLB",
      "price": 69.17,
      "scanned_at": "2026-07-21T11:31:06.554189-04:00",
      "timeframes": {
        "5Min": {
          "labels": [
            "2U",
            "2U",
            "2U"
          ],
          "high": 69.28,
          "low": 69.04,
          "last_bar": "2026-07-21T11:25:00-04:00"
        },
        "15Min": {
          "labels": [
            "1",
            "2U",
            "2U"
          ],
          "high": 69.28,
          "low": 68.71,
          "last_bar": "2026-07-21T11:15:00-04:00"
        },
        "30Min": {
          "labels": [
            "2U",
            "2U",
            "1"
          ],
          "high": 69.28,
          "low": 68.05,
          "last_bar": "2026-07-21T11:00:00-04:00"
        },
        "1H": {
          "labels": [
            "2D",
            "2U",
            "2U"
          ],
          "high": 69.32,
          "low": 67.83,
          "last_bar": "2026-07-21T10:30:00-04:00"
        },
        "2H": {
          "labels": [
            "1",
            "3",
            "2U"
          ],
          "high": 69.32,
          "low": 65.9,
          "last_bar": "2026-07-21T09:30:00-04:00"
        },
        "4H": {
          "labels": [
            "1",
            "2D",
            "2D"
          ],
          "high": 68.4,
          "low": 65.44,
          "last_bar": "2026-07-20T13:30:00-04:00"
        },
        "1D": {
          "labels": [
            "2D",
            "2D",
            "1"
          ],
          "high": 69.54,
          "low": 65.44,
          "last_bar": "2026-07-20T00:00:00-04:00"
        },
        "1W": {
          "labels": [
            "2U",
            "2D",
            "2D"
          ],
          "high": 82.54,
          "low": 64.51,
          "last_bar": "2026-07-13T00:00:00-04:00"
        }
      },
      "rejected": [
        {
          "pattern": "2-1-2",
          "setup_tf": "1D",
          "direction": "bull",
          "level": 69.54,
          "reasons": [
            "gate3b: FTFC 3/5 aligned < 4"
          ]
        },
        {
          "pattern": "2-1-2",
          "setup_tf": "1D",
          "direction": "bear",
          "level": 65.44,
          "reasons": [
            "gate2: nearest gating rung 0.2R < 2.0R (1W 64.51 (0.2R))"
          ]
        }
      ]
    },
    {
      "symbol": "CVNA",
      "price": 63.88,
      "scanned_at": "2026-07-21T11:31:06.633572-04:00",
      "timeframes": {
        "5Min": {
          "labels": [
            "2U",
            "2U",
            "2D"
          ],
          "high": 63.95,
          "low": 63.81,
          "last_bar": "2026-07-21T11:25:00-04:00"
        },
        "15Min": {
          "labels": [
            "2D",
            "2D",
            "2U"
          ],
          "high": 64.28,
          "low": 63.81,
          "last_bar": "2026-07-21T11:15:00-04:00"
        },
        "30Min": {
          "labels": [
            "1",
            "2U",
            "2D"
          ],
          "high": 64.28,
          "low": 63.73,
          "last_bar": "2026-07-21T11:00:00-04:00"
        },
        "1H": {
          "labels": [
            "2U",
            "2D",
            "1"
          ],
          "high": 64.49,
          "low": 63.73,
          "last_bar": "2026-07-21T10:30:00-04:00"
        },
        "2H": {
          "labels": [
            "2D",
            "2D",
            "2D"
          ],
          "high": 64.74,
          "low": 63.03,
          "last_bar": "2026-07-21T09:30:00-04:00"
        },
        "4H": {
          "labels": [
            "2D",
            "2D",
            "2D"
          ],
          "high": 64.89,
          "low": 63.8,
          "last_bar": "2026-07-20T13:30:00-04:00"
        },
        "1D": {
          "labels": [
            "3",
            "2D",
            "2D"
          ],
          "high": 67.96,
          "low": 63.8,
          "last_bar": "2026-07-20T00:00:00-04:00"
        },
        "1W": {
          "labels": [
            "2U",
            "2U",
            "2U"
          ],
          "high": 72.77,
          "low": 64.3,
          "last_bar": "2026-07-13T00:00:00-04:00"
        }
      },
      "rejected": [
        {
          "pattern": "F2U",
          "setup_tf": "4H",
          "direction": "bull",
          "level": 63.8,
          "reasons": [
            "gate2: nearest gating rung 1.4R < 2.0R (4H 64.89 (1.4R))"
          ]
        },
        {
          "pattern": "F2U",
          "setup_tf": "1D",
          "direction": "bull",
          "level": 63.8,
          "reasons": [
            "gate3b: FTFC 2/5 aligned < 4"
          ]
        }
      ]
    }
  ]
}